__init__.py
FuncionesMatematicas/__init__.py
FuncionesMatematicas/compuestos/__init__.py
FuncionesMatematicas/compuestos/funciones_avanzadas.py
FuncionesMatematicas/elementales/__init__.py
FuncionesMatematicas/elementales/funciones_basicas.py
FuncionesMatematicas-0.0.1.dist-info/LICENSE
FuncionesMatematicas-0.0.1.dist-info/METADATA
FuncionesMatematicas-0.0.1.dist-info/WHEEL
FuncionesMatematicas-0.0.1.dist-info/top_level.txt
FuncionesMatematicas-0.0.1.dist-info/RECORD
